nccut/__btn_images__/blue_line_btn.png
nccut/__btn_images__/cir_size_btn.png
nccut/__btn_images__/green_line_btn.png
nccut/__btn_images__/h_flip_btn.png
nccut/__btn_images__/orange_line_btn.png
nccut/__btn_images__/v_flip_btn.png
nccut/__init__.py
nccut/__main__.py
nccut/chain_data_file_printer.py
nccut/dropdowns.py
nccut/filedisplay.py
nccut/functions.py
nccut/homescreen.py
nccut/inlinechain.py
nccut/interactiveplot.py
nccut/logger.py
nccut/multiinlinechain.py
nccut/multiorthogonalchain.py
nccut/nccut.kv
nccut/nccut.py
nccut/netcdfconfig.py
nccut/orthogonalchain.py
nccut/orthogonalchainwidth.py
nccut/plotpopup.kv
nccut/plotpopup.py
nccut/plotwindow.kv
nccut/plotwindow.py
nccut/settingsbar.py
nccut-1.0.0.dist-info/LICENSES/BSD-3-Clause.txt
nccut-1.0.0.dist-info/LICENSES/CC0-1.0.txt
nccut-1.0.0.dist-info/METADATA
nccut-1.0.0.dist-info/WHEEL
nccut-1.0.0.dist-info/entry_points.txt
nccut-1.0.0.dist-info/RECORD
