Metadata-Version: 2.3
Name: nccut
Version: 1.0.0
Summary: NcCut is a GUI for getting pixel data from images and data values from NetCDF files along linear transects.
License: BSD-3-Clause
Keywords: NetCDF,GUI
Author: rchartra
Author-email: rchartra@uw.edu
Requires-Python: >=3.9,<4.0
Classifier: Intended Audience :: Science/Research
Classifier: License :: OSI Approved :: BSD License
Classifier: Operating System :: OS Independent
Classifier: Programming Language :: Python
Classifier: Programming Language :: Python :: 3
Classifier: Programming Language :: Python :: 3.9
Classifier: Programming Language :: Python :: 3.10
Classifier: Programming Language :: Python :: 3.11
Classifier: Programming Language :: Python :: 3.12
Classifier: Programming Language :: Python :: 3.13
Requires-Dist: Kivy (>=2.3.0,<3.0.0)
Requires-Dist: json5 (>=0.10.0,<0.11.0)
Requires-Dist: matplotlib (>=3.9.0,<4.0.0)
Requires-Dist: netCDF4 (>=1.7.1,<2.0.0)
Requires-Dist: numpy (>=2.0.0,<3.0.0)
Requires-Dist: pandas (>=2.2.2,<3.0.0)
Requires-Dist: plyer (>=2.1.0,<3.0.0)
Requires-Dist: progress (>=1.6,<2.0)
Requires-Dist: scipy (>=1.13.1,<2.0.0)
Requires-Dist: tomli (>=2.0.2,<3.0.0)
Requires-Dist: xarray (>=2024.6.0,<2025.0.0)
Project-URL: Documentation, https://nccut.readthedocs.io/en/latest/index.html
Project-URL: Repository, https://github.com/rchartra/NcCut
